dbticketspy/__init__.py
dbticketspy/tickets.py
dbticketspy-0.2.0.dist-info/LICENSE.txt
dbticketspy-0.2.0.dist-info/METADATA
dbticketspy-0.2.0.dist-info/WHEEL
dbticketspy-0.2.0.dist-info/top_level.txt
dbticketspy-0.2.0.dist-info/RECORD
