Metadata-Version: 2.1
Name: dbticketspy
Version: 0.2.0
Summary: A Python library to query the DB website for ticket information.
Author: Lorenz Stangier
Author-email: Lorenz Stangier <mail@lorenzstangier.de>
License: MIT
Classifier: Programming Language :: Python :: 3
Classifier: License :: OSI Approved :: MIT License
Classifier: Operating System :: OS Independent
License-File: LICENSE.txt
Requires-Dist: requests
